xmindconvertestlink/__init__.py
xmindconvertestlink/cli.py
xmindconvertestlink/const.py
xmindconvertestlink/loader.py
xmindconvertestlink/testlink_parser.py
xmindconvertestlink-0.1.0.dist-info/WHEEL
xmindconvertestlink-0.1.0.dist-info/METADATA
xmindconvertestlink-0.1.0.dist-info/RECORD
